unfinnigan/__init__.py
unfinnigan/finniganmatdat.py
unfinnigan/finniganmatinfo.py
unfinnigan/thermomethod.py
unfinnigan/unfinnigan.py
unfinnigan-0.0.1.dist-info/DESCRIPTION.rst
unfinnigan-0.0.1.dist-info/METADATA
unfinnigan-0.0.1.dist-info/RECORD
unfinnigan-0.0.1.dist-info/WHEEL
unfinnigan-0.0.1.dist-info/entry_points.txt
unfinnigan-0.0.1.dist-info/metadata.json
unfinnigan-0.0.1.dist-info/top_level.txt
