Metadata-Version: 2.0
Name: unfinnigan
Version: 0.0.1
Summary: Python file parsing toolkit for mass spec .raw files 
Home-page: https://github.com/draperjames/unfinnigan
Author: The Unfinnigan Development Team
Author-email: james.draper@duke.edu
License: BSD
Keywords: omics
Platform: UNKNOWN
Classifier: Development Status :: 3 - Alpha
Classifier: Intended Audience :: Developers
Classifier: Topic :: Software Development :: Build Tools
Classifier: License :: OSI Approved :: MIT License
Classifier: Programming Language :: Python :: 2.7
Requires-Dist: hachoir-core
Requires-Dist: hachoir-parser
